{
    "variants": {
        "variant=stained_glass_pane_lime_bubble": {
            "model": "chisel:stained_glass_pane_lime_bubble"
        },
        "variant=stained_glass_pane_lime_panel": {
            "model": "chisel:stained_glass_pane_lime_panel"
        },
        "variant=stained_glass_pane_lime_panel_fancy": {
            "model": "chisel:stained_glass_pane_lime_panel_fancy"
        },
        "variant=stained_glass_pane_lime_borderless": {
            "model": "chisel:stained_glass_pane_lime_borderless"
        }
    }
}